Metadata-Version: 1.1
Name: django-social-auth3
Version: 0.7.23
Summary: Django social authentication made simple. Python 3 support fork.
Home-page: https://github.com/omab/django-social-auth
Author: Matías Aguirre
Author-email: matiasaguirre@gmail.com
License: BSD
Keywords: django,openid,oauth,social auth,application
Platform: UNKNOWN
Classifier: Framework :: Django
Classifier: Development Status :: 4 - Beta
Classifier: Topic :: Internet
Classifier: License :: OSI Approved :: BSD License
Classifier: Intended Audience :: Developers
Classifier: Environment :: Web Environment
Classifier: Programming Language :: Python :: 3
